rabbitdeal/Receiver.py
rabbitdeal/Sender.py
rabbitdeal/__init__.py
rabbitdeal-0.1.3.dist-info/WHEEL
rabbitdeal-0.1.3.dist-info/METADATA
rabbitdeal-0.1.3.dist-info/RECORD
