Metadata-Version: 2.1
Name: rabbitdeal
Version: 0.1.3
Summary: 
Home-page: https://github.com/MattiooFR/package_name
Author: germangerken
Author-email: germangerken@yandex.ru
Requires-Python: >=3.10,<4.0
Classifier: Programming Language :: Python :: 3
Classifier: Programming Language :: Python :: 3.10
Requires-Dist: pika (>=1.3.0,<2.0.0)
Project-URL: Repository, https://github.com/MattiooFR/package_name
